hkube_notebook/__init__.py
hkube_notebook/api_utils.py
hkube_notebook/version.py
hkube_notebook/algorithm/__init__.py
hkube_notebook/algorithm/manager.py
hkube_notebook/config/__init__.py
hkube_notebook/config/config.py
hkube_notebook/config/utils.py
hkube_notebook/pipeline/__init__.py
hkube_notebook/pipeline/create.py
hkube_notebook/pipeline/exec.py
hkube_notebook/pipeline/progress.py
hkube_notebook/pipeline/tracker.py
hkube_notebook/test/__init__.py
hkube_notebook/test/create_test.py
hkube_notebook/test/test_alg.py
hkube_notebook/test/test_api.py
hkube_notebook/test/test_async.py
hkube_notebook/test/test_jupyter.py
hkube_notebook/test/test_algorithm/__init__.py
hkube_notebook/test/test_algorithm/engine.py
hkube_notebook/test/test_algorithm/main.py
hkube_notebook-1.0.0.dev3.dist-info/METADATA
hkube_notebook-1.0.0.dev3.dist-info/WHEEL
hkube_notebook-1.0.0.dev3.dist-info/top_level.txt
hkube_notebook-1.0.0.dev3.dist-info/RECORD
