Metadata-Version: 2.1
Name: hkube-notebook
Version: 1.0.0.dev3
Summary: hkube api for Jupyter Notebook
Home-page: UNKNOWN
Author: Amir Yiron
License: MIT
Platform: UNKNOWN
Classifier: Programming Language :: Python :: 3
Classifier: License :: OSI Approved :: MIT License
Classifier: Operating System :: OS Independent
Requires-Dist: flask (>=0.12.2)
Requires-Dist: pipreqs
Requires-Dist: tqdm (>=4.28.1)
Requires-Dist: gitpython
